odoo/addons/sale_coupon_limit/README.rst
odoo/addons/sale_coupon_limit/__init__.py
odoo/addons/sale_coupon_limit/__manifest__.py
odoo/addons/sale_coupon_limit/i18n/sale_coupon_limit.pot
odoo/addons/sale_coupon_limit/models/__init__.py
odoo/addons/sale_coupon_limit/models/sale_coupon.py
odoo/addons/sale_coupon_limit/models/sale_coupon_program.py
odoo/addons/sale_coupon_limit/models/sale_coupon_rule.py
odoo/addons/sale_coupon_limit/readme/CONFIGURE.rst
odoo/addons/sale_coupon_limit/readme/CONTRIBUTORS.rst
odoo/addons/sale_coupon_limit/readme/DESCRIPTION.rst
odoo/addons/sale_coupon_limit/readme/USAGE.rst
odoo/addons/sale_coupon_limit/security/ir.model.access.csv
odoo/addons/sale_coupon_limit/static/description/icon.png
odoo/addons/sale_coupon_limit/static/description/icon.svg
odoo/addons/sale_coupon_limit/static/description/index.html
odoo/addons/sale_coupon_limit/tests/__init__.py
odoo/addons/sale_coupon_limit/tests/test_sale_coupon_limit.py
odoo/addons/sale_coupon_limit/views/sale_coupon_program_views.xml
odoo13_addon_sale_coupon_limit-13.0.1.1.5.dist-info/METADATA
odoo13_addon_sale_coupon_limit-13.0.1.1.5.dist-info/WHEEL
odoo13_addon_sale_coupon_limit-13.0.1.1.5.dist-info/top_level.txt
odoo13_addon_sale_coupon_limit-13.0.1.1.5.dist-info/RECORD
