Metadata-Version: 2.1
Name: odoo13-addon-sale-coupon-limit
Version: 13.0.1.1.5
Summary: Restrict number of promotions per customer or salesman
Home-page: https://github.com/OCA/sale-promotion
Author: Tecnativa, Odoo Community Association (OCA)
Author-email: support@odoo-community.org
License: AGPL-3
Platform: UNKNOWN
Classifier: Programming Language :: Python
Classifier: Framework :: Odoo
Classifier: Framework :: Odoo :: 13.0
Classifier: License :: OSI Approved :: GNU Affero General Public License v3
Classifier: Development Status :: 4 - Beta
Requires-Python: >=3.5
Requires-Dist: odoo13-addon-sale-commercial-partner
Requires-Dist: odoo13-addon-sale-coupon-order-line-link
Requires-Dist: odoo (<13.1dev,>=13.0a)
